allure_pytest/__init__.py
allure_pytest/compat.py
allure_pytest/helper.py
allure_pytest/listener.py
allure_pytest/plugin.py
allure_pytest/utils.py
allure_pytest-2.13.5.dist-info/METADATA
allure_pytest-2.13.5.dist-info/WHEEL
allure_pytest-2.13.5.dist-info/entry_points.txt
allure_pytest-2.13.5.dist-info/top_level.txt
allure_pytest-2.13.5.dist-info/RECORD
